{
    "autoTransferIndex": 1,
    "image_name": "RedmiK40_1_jinritoutiao_20211027_b5_130.jpg",
    "objects": [
        {
            "region_attributes": {
                "transcription": "",
                "propertyName": "作者",
                "templateId": "",
                "pid": 12009,
                "propertyColor": "#00B2FF",
                "image_quality": ""
            },
            "process_attributes": {
                "taskUnitIdForDraw": 7596962,
                "processTypeForDraw": "ANNOTATION"
            },
            "shape_attributes": {
                "name": "rect",
                "x": 38,
                "y": 416,
                "width": 167,
                "height": 35
            }
        },
        {
            "region_attributes": {
                "transcription": "",
                "propertyName": "评论",
                "templateId": "",
                "pid": 12010,
                "propertyColor": "#3CFF00",
                "image_quality": ""
            },
            "process_attributes": {
                "taskUnitIdForDraw": 7596962,
                "processTypeForDraw": "ANNOTATION"
            },
            "shape_attributes": {
                "name": "rect",
                "x": 225,
                "y": 418,
                "width": 147,
                "height": 35
            }
        },
        {
            "region_attributes": {
                "transcription": "",
                "propertyName": "时间",
                "templateId": "",
                "pid": 12011,
                "propertyColor": "#00FFFF",
                "image_quality": ""
            },
            "process_attributes": {
                "taskUnitIdForDraw": 7596962,
                "processTypeForDraw": "ANNOTATION"
            },
            "shape_attributes": {
                "name": "rect",
                "x": 389,
                "y": 415,
                "width": 125,
                "height": 36
            }
        },
        {
            "region_attributes": {
                "transcription": "",
                "propertyName": "图像",
                "templateId": "",
                "pid": 12008,
                "propertyColor": "#FB00FF",
                "image_quality": ""
            },
            "process_attributes": {
                "taskUnitIdForDraw": 7596962,
                "processTypeForDraw": "ANNOTATION"
            },
            "shape_attributes": {
                "name": "rect",
                "x": 35,
                "y": 145,
                "width": 334,
                "height": 256
            }
        },
        {
            "region_attributes": {
                "transcription": "",
                "propertyName": "图像",
                "templateId": "",
                "pid": 12008,
                "propertyColor": "#FB00FF",
                "image_quality": ""
            },
            "process_attributes": {
                "taskUnitIdForDraw": 7596962,
                "processTypeForDraw": "ANNOTATION"
            },
            "shape_attributes": {
                "name": "rect",
                "x": 368,
                "y": 145,
                "width": 333,
                "height": 255
            }
        },
        {
            "region_attributes": {
                "transcription": "",
                "propertyName": "图像",
                "templateId": "",
                "pid": 12008,
                "propertyColor": "#FB00FF",
                "image_quality": ""
            },
            "process_attributes": {
                "taskUnitIdForDraw": 7596962,
                "processTypeForDraw": "ANNOTATION"
            },
            "shape_attributes": {
                "name": "rect",
                "x": 701,
                "y": 145,
                "width": 332,
                "height": 255
            }
        },
        {
            "region_attributes": {
                "transcription": "",
                "propertyName": "标题",
                "templateId": "",
                "pid": 12007,
                "propertyColor": "#FFD900",
                "image_quality": ""
            },
            "process_attributes": {
                "taskUnitIdForDraw": 7596962,
                "processTypeForDraw": "ANNOTATION"
            },
            "shape_attributes": {
                "name": "rect",
                "x": 37,
                "y": 31,
                "width": 960,
                "height": 105
            }
        },
        {
            "region_attributes": {
                "propertyName": "图文"
            },
            "shape_attributes": {
                "name": "card",
                "x": 0,
                "y": 0,
                "width": 1072,
                "height": 490
            }
        }
    ],
    "is_card_added": "true"
}